setup.py
flops/__init__.py
flops/client.py
flops/exceptions.py
flops/helpers.py
flops/validators.py
flops.egg-info/PKG-INFO
flops.egg-info/SOURCES.txt
flops.egg-info/dependency_links.txt
flops.egg-info/requires.txt
flops.egg-info/top_level.txt