Metadata-Version: 1.1
Name: flops
Version: 0.1.4
Summary: Python library to easy access flops.ru API.
Home-page: https://github.com/atuchak/python-flops
Author: Anton Tuchak
Author-email: anton.tuchak@gmail.com
License: UNKNOWN
Keywords: flops.ru API client flops
Platform: UNKNOWN
Classifier: Intended Audience :: Developers
Classifier: Development Status :: 5 - Production/Stable
Classifier: Operating System :: OS Independent
Classifier: Programming Language :: Python :: 2
Classifier: Programming Language :: Python :: 3
Classifier: Topic :: Internet :: WWW/HTTP
